aprsd/__init__.py
aprsd/cli_helper.py
aprsd/exception.py
aprsd/main.py
aprsd/plugin.py
aprsd/plugin_utils.py
aprsd/client/__init__.py
aprsd/client/client.py
aprsd/client/stats.py
aprsd/client/drivers/__init__.py
aprsd/client/drivers/aprsis.py
aprsd/client/drivers/fake.py
aprsd/client/drivers/registry.py
aprsd/client/drivers/tcpkiss.py
aprsd/client/drivers/lib/__init__.py
aprsd/client/drivers/lib/aprslib.py
aprsd/cmds/__init__.py
aprsd/cmds/completion.py
aprsd/cmds/dev.py
aprsd/cmds/fetch_stats.py
aprsd/cmds/healthcheck.py
aprsd/cmds/list_plugins.py
aprsd/cmds/listen.py
aprsd/cmds/send_message.py
aprsd/cmds/server.py
aprsd/conf/__init__.py
aprsd/conf/client.py
aprsd/conf/common.py
aprsd/conf/log.py
aprsd/conf/opts.py
aprsd/conf/plugin_common.py
aprsd/log/__init__.py
aprsd/log/log.py
aprsd/packets/__init__.py
aprsd/packets/collector.py
aprsd/packets/core.py
aprsd/packets/filter.py
aprsd/packets/log.py
aprsd/packets/packet_list.py
aprsd/packets/seen_list.py
aprsd/packets/tracker.py
aprsd/packets/watch_list.py
aprsd/packets/filters/__init__.py
aprsd/packets/filters/dupe_filter.py
aprsd/packets/filters/packet_type.py
aprsd/plugins/__init__.py
aprsd/plugins/fortune.py
aprsd/plugins/notify.py
aprsd/plugins/ping.py
aprsd/plugins/time.py
aprsd/plugins/version.py
aprsd/plugins/weather.py
aprsd/stats/__init__.py
aprsd/stats/app.py
aprsd/stats/collector.py
aprsd/threads/__init__.py
aprsd/threads/aprsd.py
aprsd/threads/keepalive.py
aprsd/threads/registry.py
aprsd/threads/rx.py
aprsd/threads/service.py
aprsd/threads/stats.py
aprsd/threads/tx.py
aprsd/utils/__init__.py
aprsd/utils/counter.py
aprsd/utils/fuzzyclock.py
aprsd/utils/json.py
aprsd/utils/keepalive_collector.py
aprsd/utils/objectstore.py
aprsd/utils/package.py
aprsd/utils/ring_buffer.py
aprsd/utils/trace.py
aprsd-4.2.4.dist-info/licenses/AUTHORS
aprsd-4.2.4.dist-info/licenses/LICENSE
aprsd-4.2.4.dist-info/METADATA
aprsd-4.2.4.dist-info/WHEEL
aprsd-4.2.4.dist-info/entry_points.txt
aprsd-4.2.4.dist-info/top_level.txt
aprsd-4.2.4.dist-info/RECORD
