Metadata-Version: 2.4
Name: aprsd
Version: 4.2.4
Summary: APRSd is a APRS-IS server that can be used to connect to APRS-IS and send and receive APRS packets.
Author-email: Craig Lamparter <craig@craiger.org>, "Walter A. Boring IV" <waboring@hemna.com>, Emre Saglam <emresaglam@gmail.com>, Jason Martin <jhmartin@toger.us>, John <johng42@users.noreply.github.com>, Martiros Shakhzadyan <vrzh@vrzh.net>, Zoe Moore <zoenb@mailbox.org>, ranguli <hello@joshmurphy.ca>
Maintainer-email: Craig Lamparter <craig@craiger.org>, "Walter A. Boring IV" <waboring@hemna.com>
License: 
Project-URL: Homepage, https://github.com/craigerl/aprsd
Project-URL: Bug Reports, https://github.com/craigerl/aprsd/issues
Project-URL: Source, https://github.com/craigerl/aprsd
Keywords: aprs,aprs-is,aprsd,aprsd-server,aprsd-client,aprsd-socket,aprsd-socket-server,aprsd-socket-client
Classifier: Development Status :: 5 - Production/Stable
Classifier: Environment :: Console
Classifier: Intended Audience :: Developers
Classifier: Intended Audience :: End Users/Desktop
Classifier: Intended Audience :: Information Technology
Classifier: Topic :: Communications :: Ham Radio
Classifier: Topic :: Internet
Classifier: Programming Language :: Python :: 3 :: Only
Classifier: Programming Language :: Python :: 3
Classifier: Programming Language :: Python :: 3.8
Classifier: Programming Language :: Python :: 3.9
Classifier: Programming Language :: Python :: 3.10
Classifier: Programming Language :: Python :: 3.11
Requires-Python: >=3.10
License-File: LICENSE
License-File: AUTHORS
Requires-Dist: aprslib==0.7.2
Requires-Dist: attrs==25.3.0
Requires-Dist: ax253==0.1.5.post1
Requires-Dist: bitarray==3.6.1
Requires-Dist: certifi==2025.8.3
Requires-Dist: charset-normalizer==3.4.3
Requires-Dist: click==8.2.1
Requires-Dist: dataclasses-json==0.6.7
Requires-Dist: haversine==2.9.0
Requires-Dist: idna==3.10
Requires-Dist: importlib-metadata==8.7.0
Requires-Dist: kiss3==8.0.0
Requires-Dist: loguru==0.7.3
Requires-Dist: markdown-it-py==4.0.0
Requires-Dist: marshmallow==3.26.1
Requires-Dist: mdurl==0.1.2
Requires-Dist: mypy-extensions==1.1.0
Requires-Dist: netaddr==1.3.0
Requires-Dist: oslo-config==10.0.0
Requires-Dist: oslo-i18n==6.5.1
Requires-Dist: packaging==25.0
Requires-Dist: pbr==6.1.1
Requires-Dist: pluggy==1.6.0
Requires-Dist: pygments==2.19.2
Requires-Dist: pyserial==3.5
Requires-Dist: pyserial-asyncio==0.6
Requires-Dist: pytz==2025.2
Requires-Dist: pyyaml==6.0.2
Requires-Dist: requests==2.32.4
Requires-Dist: rfc3986==2.0.0
Requires-Dist: rich==14.1.0
Requires-Dist: rush==2021.4.0
Requires-Dist: setuptools==80.9.0
Requires-Dist: stevedore==5.4.1
Requires-Dist: thesmuggler==1.0.1
Requires-Dist: timeago==1.0.16
Requires-Dist: typing-extensions==4.14.1
Requires-Dist: typing-inspect==0.9.0
Requires-Dist: tzlocal==5.3.1
Requires-Dist: update-checker==0.18.0
Requires-Dist: urllib3==2.5.0
Requires-Dist: wrapt==1.17.3
Requires-Dist: zipp==3.23.0
Provides-Extra: dev
Requires-Dist: alabaster==1.0.0; extra == "dev"
Requires-Dist: babel==2.17.0; extra == "dev"
Requires-Dist: build==1.3.0; extra == "dev"
Requires-Dist: cachetools==6.1.0; extra == "dev"
Requires-Dist: certifi==2025.8.3; extra == "dev"
Requires-Dist: cfgv==3.4.0; extra == "dev"
Requires-Dist: chardet==5.2.0; extra == "dev"
Requires-Dist: charset-normalizer==3.4.3; extra == "dev"
Requires-Dist: click==8.2.1; extra == "dev"
Requires-Dist: colorama==0.4.6; extra == "dev"
Requires-Dist: distlib==0.4.0; extra == "dev"
Requires-Dist: docutils==0.21.2; extra == "dev"
Requires-Dist: filelock==3.18.0; extra == "dev"
Requires-Dist: identify==2.6.13; extra == "dev"
Requires-Dist: idna==3.10; extra == "dev"
Requires-Dist: imagesize==1.4.1; extra == "dev"
Requires-Dist: jinja2==3.1.6; extra == "dev"
Requires-Dist: m2r==0.3.1; extra == "dev"
Requires-Dist: markupsafe==3.0.2; extra == "dev"
Requires-Dist: mistune==0.8.4; extra == "dev"
Requires-Dist: nodeenv==1.9.1; extra == "dev"
Requires-Dist: packaging==25.0; extra == "dev"
Requires-Dist: pip==25.2; extra == "dev"
Requires-Dist: pip-tools==7.5.0; extra == "dev"
Requires-Dist: platformdirs==4.3.8; extra == "dev"
Requires-Dist: pluggy==1.6.0; extra == "dev"
Requires-Dist: pre-commit==4.3.0; extra == "dev"
Requires-Dist: pygments==2.19.2; extra == "dev"
Requires-Dist: pyproject-api==1.9.1; extra == "dev"
Requires-Dist: pyproject-hooks==1.2.0; extra == "dev"
Requires-Dist: pyyaml==6.0.2; extra == "dev"
Requires-Dist: requests==2.32.4; extra == "dev"
Requires-Dist: setuptools==80.9.0; extra == "dev"
Requires-Dist: snowballstemmer==3.0.1; extra == "dev"
Requires-Dist: sphinx==8.1.3; extra == "dev"
Requires-Dist: sphinxcontrib-applehelp==2.0.0; extra == "dev"
Requires-Dist: sphinxcontrib-devhelp==2.0.0; extra == "dev"
Requires-Dist: sphinxcontrib-htmlhelp==2.1.0; extra == "dev"
Requires-Dist: sphinxcontrib-jsmath==1.0.1; extra == "dev"
Requires-Dist: sphinxcontrib-qthelp==2.0.0; extra == "dev"
Requires-Dist: sphinxcontrib-serializinghtml==2.0.0; extra == "dev"
Requires-Dist: tomli==2.2.1; extra == "dev"
Requires-Dist: tox==4.28.4; extra == "dev"
Requires-Dist: typing-extensions==4.14.1; extra == "dev"
Requires-Dist: urllib3==2.5.0; extra == "dev"
Requires-Dist: virtualenv==20.33.1; extra == "dev"
Requires-Dist: wheel==0.45.1; extra == "dev"
Dynamic: license-file
